setup.py
bin/abridge-db
bin/abridger-dump-relations
lib/abridger/__init__.py
lib/abridger/abridge_db.py
lib/abridger/config_file_loader.py
lib/abridger/dump_relations.py
lib/abridger/exc.py
lib/abridger/generator.py
lib/abridger.egg-info/PKG-INFO
lib/abridger.egg-info/SOURCES.txt
lib/abridger.egg-info/dependency_links.txt
lib/abridger.egg-info/requires.txt
lib/abridger.egg-info/top_level.txt
lib/abridger/database/__init__.py
lib/abridger/database/base.py
lib/abridger/database/postgresql.py
lib/abridger/database/sqlite.py
lib/abridger/extraction_model/__init__.py
lib/abridger/extraction_model/model.py
lib/abridger/extraction_model/not_null_column.py
lib/abridger/extraction_model/relation.py
lib/abridger/extraction_model/subject.py
lib/abridger/extraction_model/table.py
lib/abridger/extractor/__init__.py
lib/abridger/extractor/results_row.py
lib/abridger/extractor/work_item.py
lib/abridger/schema/__init__.py
lib/abridger/schema/base.py
lib/abridger/schema/postgresql.py
lib/abridger/schema/sqlite.py